{
  "default": {
    "0.0.9": 6245,
    "0.0.8": 887,
    "0.0.7": 63828,
    "0.0.6": 30469,
    "0.0.5": 40,
    "0.0.4": 8,
    "0.0.3": 5,
    "0.0.2": 9,
    "downloads": 101491,
    "updated": 1700246373000
  },
  "dalle": {
    "0.1.0": 576,
    "0.0.9": 474,
    "0.0.6": 319,
    "0.0.5": 2239,
    "0.0.4": 3966,
    "0.0.3": 93733,
    "0.0.2": 90,
    "0.0.1": 7,
    "downloads": 101404,
    "updated": 1713268558000
  },
  "huggingface": {
    "0.0.4": 7657,
    "0.0.3": 65807,
    "0.0.2": 27753,
    "0.0.1": 537,
    "downloads": 101754,
    "updated": 1698764528000
  },
  "awesomePrompts": {
    "0.0.3": 5654,
    "0.0.2": 1729,
    "0.0.1": 1,
    "downloads": 7384,
    "updated": 1701203329000
  },
  "tts": {
    "0.0.3": 3499,
    "0.0.2": 230,
    "downloads": 3729,
    "updated": 1705577881000
  },
  "vision": {
    "0.0.2": 3424,
    "0.0.1": 302,
    "downloads": 3726,
    "updated": 1705739731000
  },
  "smartConnections": {
    "0.0.1": 3725,
    "downloads": 3725,
    "updated": 1705072626000
  },
  "Experimental": {
    "0.0.2": 3187,
    "0.0.1": 386,
    "downloads": 3573,
    "updated": 1706234800000
  }
}