{
  "default": {
    "0.0.9": 10004,
    "0.0.8": 889,
    "0.0.7": 63830,
    "0.0.6": 30471,
    "0.0.5": 41,
    "0.0.4": 10,
    "0.0.3": 7,
    "0.0.2": 11,
    "downloads": 105263,
    "updated": 1700246373000
  },
  "dalle": {
    "0.1.1": 3725,
    "0.1.0": 618,
    "0.0.9": 475,
    "0.0.8": 1,
    "0.0.7": 1,
    "0.0.6": 320,
    "0.0.5": 2240,
    "0.0.4": 3967,
    "0.0.3": 93734,
    "0.0.2": 91,
    "0.0.1": 8,
    "downloads": 105180,
    "updated": 1715415097000
  },
  "huggingface": {
    "0.0.4": 11409,
    "0.0.3": 65808,
    "0.0.2": 27754,
    "0.0.1": 538,
    "downloads": 105509,
    "updated": 1698764528000
  },
  "awesomePrompts": {
    "0.0.3": 9406,
    "0.0.2": 1730,
    "0.0.1": 2,
    "downloads": 11138,
    "updated": 1701203329000
  },
  "tts": {
    "0.0.3": 7249,
    "0.0.2": 231,
    "0.0.1": 1,
    "downloads": 7481,
    "updated": 1705577881000
  },
  "vision": {
    "0.0.2": 7176,
    "0.0.1": 303,
    "downloads": 7479,
    "updated": 1705739731000
  },
  "smartConnections": {
    "0.0.1": 7478,
    "downloads": 7478,
    "updated": 1705072626000
  },
  "Experimental": {
    "0.0.2": 6940,
    "0.0.1": 387,
    "downloads": 7327,
    "updated": 1706234800000
  }
}