{
  "default": {
    "0.0.7": 59230,
    "0.0.6": 30469,
    "0.0.5": 40,
    "0.0.4": 8,
    "0.0.3": 5,
    "0.0.2": 9,
    "downloads": 89761,
    "updated": 1671631669000
  },
  "dalle-2": {
    "0.0.3": 89014,
    "0.0.2": 90,
    "0.0.1": 7,
    "downloads": 89111,
    "updated": 1669876979000
  },
  "huggingface": {
    "0.0.3": 61070,
    "0.0.2": 27753,
    "0.0.1": 537,
    "downloads": 89360,
    "updated": 1671557984000
  },
  "awesomechatgpt": {
    "0.0.3": 12082,
    "0.0.2": 1,
    "0.0.1": 4,
    "downloads": 12087,
    "updated": 1682431028000
  }
}